LICENSE
README.md
setup.py
pydantic_cli/__init__.py
pydantic_cli/_compat.py
pydantic_cli/_version.py
pydantic_cli/argparse.py
pydantic_cli/core.py
pydantic_cli/py.typed
pydantic_cli/shell_completion.py
pydantic_cli/utils.py
pydantic_cli/examples/__init__.py
pydantic_cli/examples/simple.py
pydantic_cli/examples/simple_schema.py
pydantic_cli/examples/simple_with_boolean.py
pydantic_cli/examples/simple_with_boolean_and_config.py
pydantic_cli/examples/simple_with_boolean_custom.py
pydantic_cli/examples/simple_with_custom.py
pydantic_cli/examples/simple_with_custom_and_setup_log.py
pydantic_cli/examples/simple_with_enum.py
pydantic_cli/examples/simple_with_enum_by_name.py
pydantic_cli/examples/simple_with_json_config.py
pydantic_cli/examples/simple_with_json_config_not_found.py
pydantic_cli/examples/simple_with_list.py
pydantic_cli/examples/simple_with_shell_autocomplete_support.py
pydantic_cli/examples/subparser.py
pydantic_cli_pydantic_v2_compatible.egg-info/PKG-INFO
pydantic_cli_pydantic_v2_compatible.egg-info/SOURCES.txt
pydantic_cli_pydantic_v2_compatible.egg-info/dependency_links.txt
pydantic_cli_pydantic_v2_compatible.egg-info/not-zip-safe
pydantic_cli_pydantic_v2_compatible.egg-info/requires.txt
pydantic_cli_pydantic_v2_compatible.egg-info/top_level.txt