Metadata-Version: 2.1
Name: pydantic_cli_pydantic_v2_compatible
Version: 4.4.0
Summary: Turn Pydantic defined Data Models into CLI Tools
Home-page: http://github.com/mpkocher/pydantic-cli
Author: M. Kocher
Author-email: michael.kocher@me.com
License: MIT
Classifier: Programming Language :: Python :: 3
Classifier: Programming Language :: Python :: 3.7
Classifier: Programming Language :: Python :: 3.8
Classifier: Programming Language :: Python :: 3.9
Classifier: License :: OSI Approved :: MIT License
Classifier: Operating System :: OS Independent
Classifier: Topic :: Utilities
Classifier: Topic :: Software Development
Classifier: Typing :: Typed
Requires-Python: >=3.7
License-File: LICENSE
Requires-Dist: pydantic==2.7.1
Requires-Dist: pydantic-core==2.18.2
Requires-Dist: typing-extensions==4.11.0
Provides-Extra: shtab
Requires-Dist: shtab>=1.3.1; extra == "shtab"
